tree_sitter_apertium-0.1.9.dist-info/RECORD
tree_sitter_apertium-0.1.9.dist-info/top_level.txt
tree_sitter_apertium-0.1.9.dist-info/METADATA
tree_sitter_apertium-0.1.9.dist-info/WHEEL
tree_sitter_apertium/langs.so
tree_sitter_apertium/__init__.py
