Metadata-Version: 2.1
Name: tree-sitter-apertium
Version: 0.1.9
Summary: tree-sitter grammars for Apertium formats
Home-page: https://github.com/apertium/tree-sitter-apertium
Author: Daniel Swanson
Author-email: awesomeevildudes@gmail.com
Classifier: Development Status :: 1 - Planning
Classifier: Intended Audience :: Developers
Classifier: License :: OSI Approved :: GNU General Public License v3 or later (GPLv3+)
Classifier: Programming Language :: Python :: 3 :: Only
Classifier: Topic :: Text Processing :: Linguistic
Requires-Dist: tree-sitter (>=0.20)
